[
    [
        {
            "ID": 4,
            "Row": 4,
            "CompanyID": 1177,
            "YearPeriod": 2011,
            "TermCode": "N",
            "TermName": "Năm",
            "TermNameEN": "Year",
            "ReportTermID": 1,
            "DisplayOrdering": 1,
            "United": "",
            "AuditedStatus": "",
            "PeriodBegin": "201101",
            "PeriodEnd": "201112",
            "TotalRow": 12,
            "BusinessType": 3,
            "ReportNote": null,
            "ReportNoteEn": null
        },
        {
            "ID": 3,
            "Row": 3,
            "CompanyID": 1177,
            "YearPeriod": 2012,
            "TermCode": "N",
            "TermName": "Năm",
            "TermNameEN": "Year",
            "ReportTermID": 1,
            "DisplayOrdering": 1,
            "United": "",
            "AuditedStatus": "",
            "PeriodBegin": "201201",
            "PeriodEnd": "201212",
            "TotalRow": 12,
            "BusinessType": 3,
            "ReportNote": null,
            "ReportNoteEn": null
        },
        {
            "ID": 2,
            "Row": 2,
            "CompanyID": 1177,
            "YearPeriod": 2013,
            "TermCode": "N",
            "TermName": "Năm",
            "TermNameEN": "Year",
            "ReportTermID": 1,
            "DisplayOrdering": 1,
            "United": "",
            "AuditedStatus": "",
            "PeriodBegin": "201301",
            "PeriodEnd": "201312",
            "TotalRow": 12,
            "BusinessType": 3,
            "ReportNote": null,
            "ReportNoteEn": null
        },
        {
            "ID": 1,
            "Row": 1,
            "CompanyID": 1177,
            "YearPeriod": 2014,
            "TermCode": "N",
            "TermName": "Năm",
            "TermNameEN": "Year",
            "ReportTermID": 1,
            "DisplayOrdering": 1,
            "United": "",
            "AuditedStatus": "",
            "PeriodBegin": "201401",
            "PeriodEnd": "201412",
            "TotalRow": 12,
            "BusinessType": 3,
            "ReportNote": null,
            "ReportNoteEn": null
        }
    ],
    {
        "Valuation ratios": [
            {
                "ID": 1,
                "ReportNormID": 53,
                "Name": "Thu nhập trên mỗi cổ phần của 4 quý gần nhất (EPS)",
                "NameEn": "Trailing EPS",
                "NameMobile": "Thu nhập trên mỗi cổ phần của 4 quý gần nhất (EPS)",
                "NameMobileEn": "Trailing EPS",
                "CssStyle": "",
                "Padding": "Padding1",
                "ParentReportNormID": 0,
                "ReportComponentName": "Nhóm chỉ số Định giá",
                "ReportComponentNameEn": "Valuation ratios",
                "Unit": "VNĐ",
                "UnitEn": "VND",
                "OrderType": null,
                "OrderingComponent": null,
                "RowNumber": null,
                "ReportComponentTypeID": 9,
                "ChildTotal": 0,
                "Levels": 0,
                "Value1": 2023.0,
                "Value2": 4120.0,
                "Value3": 6837.0,
                "Value4": 6500.0,
                "Vl": null,
                "IsShowData": true
            },
            {
                "ID": 2,
                "ReportNormID": 54,
                "Name": "Giá trị sổ sách của cổ phiếu (BVPS)",
                "NameEn": "Book value per share (BVPS)",
                "NameMobile": "Giá trị sổ sách của cổ phiếu (BVPS)",
                "NameMobileEn": "Book value per share (BVPS)",
                "CssStyle": "",
                "Padding": "Padding1",
                "ParentReportNormID": 0,
                "ReportComponentName": "Nhóm chỉ số Định giá",
                "ReportComponentNameEn": "Valuation ratios",
                "Unit": "VNĐ",
                "UnitEn": "VND",
                "OrderType": null,
                "OrderingComponent": null,
                "RowNumber": null,
                "ReportComponentTypeID": 9,
                "ChildTotal": 0,
                "Levels": 0,
                "Value1": 11284.0,
                "Value2": 11770.0,
                "Value3": 12208.0,
                "Value4": 12919.0,
                "Vl": null,
                "IsShowData": true
            },
            {
                "ID": 3,
                "ReportNormID": 55,
                "Name": "Chỉ số giá thị trường trên thu nhập (P/E)",
                "NameEn": "P/E",
                "NameMobile": "Chỉ số giá thị trường trên thu nhập (P/E)",
                "NameMobileEn": "P/E",
                "CssStyle": "",
                "Padding": "Padding1",
                "ParentReportNormID": 0,
                "ReportComponentName": "Nhóm chỉ số Định giá",
                "ReportComponentNameEn": "Valuation ratios",
                "Unit": "Lần",
                "UnitEn": "Times",
                "OrderType": null,
                "OrderingComponent": null,
                "RowNumber": null,
                "ReportComponentTypeID": 9,
                "ChildTotal": 0,
                "Levels": 0,
                "Value1": 0.0,
                "Value2": 0.0,
                "Value3": 0.0,
                "Value4": 0.0,
                "Vl": null,
                "IsShowData": true
            },
            {
                "ID": 4,
                "ReportNormID": 57,
                "Name": "Chỉ số giá thị trường trên giá trị sổ sách (P/B)",
                "NameEn": "P/B",
                "NameMobile": "Chỉ số giá thị trường trên giá trị sổ sách (P/B)",
                "NameMobileEn": "P/B",
                "CssStyle": "",
                "Padding": "Padding1",
                "ParentReportNormID": 0,
                "ReportComponentName": "Nhóm chỉ số Định giá",
                "ReportComponentNameEn": "Valuation ratios",
                "Unit": "Lần",
                "UnitEn": "Times",
                "OrderType": null,
                "OrderingComponent": null,
                "RowNumber": null,
                "ReportComponentTypeID": 9,
                "ChildTotal": 0,
                "Levels": 0,
                "Value1": 0.0,
                "Value2": 0.0,
                "Value3": 0.0,
                "Value4": 0.0,
                "Vl": null,
                "IsShowData": true
            },
            {
                "ID": 5,
                "ReportNormID": 60,
                "Name": "Tỷ suất cổ tức",
                "NameEn": "Dividend yield",
                "NameMobile": "Tỷ suất cổ tức",
                "NameMobileEn": "Dividend yield",
                "CssStyle": "",
                "Padding": "Padding1",
                "ParentReportNormID": 0,
                "ReportComponentName": "Nhóm chỉ số Định giá",
                "ReportComponentNameEn": "Valuation ratios",
                "Unit": "%",
                "UnitEn": "%",
                "OrderType": null,
                "OrderingComponent": null,
                "RowNumber": null,
                "ReportComponentTypeID": 9,
                "ChildTotal": 0,
                "Levels": 0,
                "Value1": 0.0,
                "Value2": 0.0,
                "Value3": 0.0,
                "Value4": 0.0,
                "Vl": null,
                "IsShowData": true
            },
            {
                "ID": 6,
                "ReportNormID": 61,
                "Name": "Beta",
                "NameEn": "Beta",
                "NameMobile": "Beta",
                "NameMobileEn": "Beta",
                "CssStyle": "",
                "Padding": "Padding1",
                "ParentReportNormID": 0,
                "ReportComponentName": "Nhóm chỉ số Định giá",
                "ReportComponentNameEn": "Valuation ratios",
                "Unit": "",
                "UnitEn": "",
                "OrderType": null,
                "OrderingComponent": null,
                "RowNumber": null,
                "ReportComponentTypeID": 9,
                "ChildTotal": 0,
                "Levels": 0,
                "Value1": 0.0,
                "Value2": 0.0,
                "Value3": 0.0,
                "Value4": 0.0,
                "Vl": null,
                "IsShowData": true
            }
        ],
        "Profitability ratios": [
            {
                "ID": 7,
                "ReportNormID": 45,
                "Name": "Tỷ suất lợi nhuận trên vốn chủ sở hữu bình quân (ROEA)",
                "NameEn": "ROE",
                "NameMobile": "Tỷ suất lợi nhuận trên vốn chủ sở hữu bình quân (ROEA)",
                "NameMobileEn": "ROE",
                "CssStyle": "",
                "Padding": "Padding1",
                "ParentReportNormID": 0,
                "ReportComponentName": "Nhóm chỉ số Sinh lợi",
                "ReportComponentNameEn": "Profitability ratios",
                "Unit": "%",
                "UnitEn": "%",
                "OrderType": null,
                "OrderingComponent": null,
                "RowNumber": null,
                "ReportComponentTypeID": 2,
                "ChildTotal": 0,
                "Levels": 0,
                "Value1": 0.47,
                "Value2": 5.47,
                "Value3": 9.69,
                "Value4": 16.86,
                "Vl": null,
                "IsShowData": true
            },
            {
                "ID": 8,
                "ReportNormID": 47,
                "Name": "Tỷ suất sinh lợi trên tổng tài sản bình quân (ROAA)",
                "NameEn": "ROA",
                "NameMobile": "Tỷ suất sinh lợi trên tổng tài sản bình quân (ROAA)",
                "NameMobileEn": "ROA",
                "CssStyle": "",
                "Padding": "Padding1",
                "ParentReportNormID": 0,
                "ReportComponentName": "Nhóm chỉ số Sinh lợi",
                "ReportComponentNameEn": "Profitability ratios",
                "Unit": "%",
                "UnitEn": "%",
                "OrderType": null,
                "OrderingComponent": null,
                "RowNumber": null,
                "ReportComponentTypeID": 2,
                "ChildTotal": 0,
                "Levels": 0,
                "Value1": 0.03,
                "Value2": 0.46,
                "Value3": 0.86,
                "Value4": 1.56,
                "Vl": null,
                "IsShowData": true
            },
            {
                "ID": 9,
                "ReportNormID": 106,
                "Name": "Tỷ suất sinh lợi của Tài sản Có sinh lãi (YOEA)",
                "NameEn": "Yield on earning assets (YOEA)",
                "NameMobile": "Tỷ suất sinh lợi của Tài sản Có sinh lãi (YOEA)",
                "NameMobileEn": "Yield on earning assets (YOEA)",
                "CssStyle": "",
                "Padding": "Padding1",
                "ParentReportNormID": 0,
                "ReportComponentName": "Nhóm chỉ số Sinh lợi",
                "ReportComponentNameEn": "Profitability ratios",
                "Unit": "%",
                "UnitEn": "%",
                "OrderType": null,
                "OrderingComponent": null,
                "RowNumber": null,
                "ReportComponentTypeID": 2,
                "ChildTotal": 0,
                "Levels": 0,
                "Value1": 8.21,
                "Value2": 10.66,
                "Value3": 13.35,
                "Value4": 15.13,
                "Vl": null,
                "IsShowData": true
            },
            {
                "ID": 10,
                "ReportNormID": 107,
                "Name": "Tỷ lệ chi phí hình thành Tài sản Có sinh lãi (COF)",
                "NameEn": "Cost of funding earning assets (COF)",
                "NameMobile": "Tỷ lệ chi phí hình thành Tài sản Có sinh lãi (COF)",
                "NameMobileEn": "Cost of funding earning assets (COF)",
                "CssStyle": "",
                "Padding": "Padding1",
                "ParentReportNormID": 0,
                "ReportComponentName": "Nhóm chỉ số Sinh lợi",
                "ReportComponentNameEn": "Profitability ratios",
                "Unit": "%",
                "UnitEn": "%",
                "OrderType": null,
                "OrderingComponent": null,
                "RowNumber": null,
                "ReportComponentTypeID": 2,
                "ChildTotal": 0,
                "Levels": 0,
                "Value1": 5.64,
                "Value2": 6.82,
                "Value3": 9.15,
                "Value4": 10.28,
                "Vl": null,
                "IsShowData": true
            },
            {
                "ID": 11,
                "ReportNormID": 108,
                "Name": "Tỷ lệ thu nhập lãi thuần (NIM)",
                "NameEn": "Net interest margin (NIM)",
                "NameMobile": "Tỷ lệ thu nhập lãi thuần (NIM)",
                "NameMobileEn": "Net interest margin (NIM)",
                "CssStyle": "",
                "Padding": "Padding1",
                "ParentReportNormID": 0,
                "ReportComponentName": "Nhóm chỉ số Sinh lợi",
                "ReportComponentNameEn": "Profitability ratios",
                "Unit": "%",
                "UnitEn": "%",
                "OrderType": null,
                "OrderingComponent": null,
                "RowNumber": null,
                "ReportComponentTypeID": 2,
                "ChildTotal": 0,
                "Levels": 0,
                "Value1": 2.18,
                "Value2": 3.61,
                "Value3": 4.46,
                "Value4": 5.08,
                "Vl": null,
                "IsShowData": true
            },
            {
                "ID": 12,
                "ReportNormID": 109,
                "Name": "Tỷ lệ chi phí hoạt động/Tổng thu nhập HĐKD trước dự phòng (CIR)",
                "NameEn": "Cost Income Ratio (CIR)",
                "NameMobile": "Tỷ lệ chi phí hoạt động/Tổng thu nhập HĐKD trước dự phòng (CIR)",
                "NameMobileEn": "Cost Income Ratio (CIR)",
                "CssStyle": "",
                "Padding": "Padding1",
                "ParentReportNormID": 0,
                "ReportComponentName": "Nhóm chỉ số Sinh lợi",
                "ReportComponentNameEn": "Profitability ratios",
                "Unit": "%",
                "UnitEn": "%",
                "OrderType": null,
                "OrderingComponent": null,
                "RowNumber": null,
                "ReportComponentTypeID": 2,
                "ChildTotal": 0,
                "Levels": 0,
                "Value1": 72.25,
                "Value2": 60.98,
                "Value3": 49.38,
                "Value4": 45.51,
                "Vl": null,
                "IsShowData": true
            }
        ],
        "Growth rates": [
            {
                "ID": 13,
                "ReportNormID": 32,
                "Name": "Tăng trưởng lợi nhuận trước thuế ",
                "NameEn": "Profit before tax",
                "NameMobile": "Tăng trưởng lợi nhuận trước thuế ",
                "NameMobileEn": "Profit before tax",
                "CssStyle": "",
                "Padding": "Padding1",
                "ParentReportNormID": 0,
                "ReportComponentName": "Nhóm chỉ số Tăng trưởng",
                "ReportComponentNameEn": "Growth rates",
                "Unit": "%",
                "UnitEn": "%",
                "OrderType": null,
                "OrderingComponent": null,
                "RowNumber": null,
                "ReportComponentTypeID": 1,
                "ChildTotal": 0,
                "Levels": 0,
                "Value1": -91.83,
                "Value2": -44.64,
                "Value3": -38.1,
                "Value4": 46.41,
                "Vl": null,
                "IsShowData": true
            },
            {
                "ID": 14,
                "ReportNormID": 33,
                "Name": "Tăng trưởng lợi nhuận sau thuế của CĐ ngân hàng mẹ",
                "NameEn": "Profit after tax for shareholders of the parent company",
                "NameMobile": "Tăng trưởng lợi nhuận sau thuế của CĐ ngân hàng mẹ",
                "NameMobileEn": "Profit after tax for shareholders of the parent company",
                "CssStyle": "",
                "Padding": "Padding1",
                "ParentReportNormID": 0,
                "ReportComponentName": "Nhóm chỉ số Tăng trưởng",
                "ReportComponentNameEn": "Growth rates",
                "Unit": "%",
                "UnitEn": "%",
                "OrderType": null,
                "OrderingComponent": null,
                "RowNumber": null,
                "ReportComponentTypeID": 1,
                "ChildTotal": 0,
                "Levels": 0,
                "Value1": -91.78,
                "Value2": -43.15,
                "Value3": -39.06,
                "Value4": 43.65,
                "Vl": null,
                "IsShowData": true
            },
            {
                "ID": 15,
                "ReportNormID": 34,
                "Name": "Tăng trưởng tổng tài sản",
                "NameEn": "Total assets",
                "NameMobile": "Tăng trưởng tổng tài sản",
                "NameMobileEn": "Total assets",
                "CssStyle": "",
                "Padding": "Padding1",
                "ParentReportNormID": 0,
                "ReportComponentName": "Nhóm chỉ số Tăng trưởng",
                "ReportComponentNameEn": "Growth rates",
                "Unit": "%",
                "UnitEn": "%",
                "OrderType": null,
                "OrderingComponent": null,
                "RowNumber": null,
                "ReportComponentTypeID": 1,
                "ChildTotal": 0,
                "Levels": 0,
                "Value1": 16.27,
                "Value2": 8.14,
                "Value3": 5.69,
                "Value4": 17.32,
                "Vl": null,
                "IsShowData": true
            },
            {
                "ID": 16,
                "ReportNormID": 37,
                "Name": "Tăng trưởng vốn chủ sở hữu",
                "NameEn": "Owner's equity",
                "NameMobile": "Tăng trưởng vốn chủ sở hữu",
                "NameMobileEn": "Owner's equity",
                "CssStyle": "",
                "Padding": "Padding1",
                "ParentReportNormID": 0,
                "ReportComponentName": "Nhóm chỉ số Tăng trưởng",
                "ReportComponentNameEn": "Growth rates",
                "Unit": "%",
                "UnitEn": "%",
                "OrderType": null,
                "OrderingComponent": null,
                "RowNumber": null,
                "ReportComponentTypeID": 1,
                "ChildTotal": 0,
                "Levels": 0,
                "Value1": -4.13,
                "Value2": -3.59,
                "Value3": 5.0,
                "Value4": 7.26,
                "Vl": null,
                "IsShowData": true
            },
            {
                "ID": 17,
                "ReportNormID": 38,
                "Name": "Tăng trưởng vốn điều lệ",
                "NameEn": "Charter capital",
                "NameMobile": "Tăng trưởng vốn điều lệ",
                "NameMobileEn": "Charter capital",
                "CssStyle": "",
                "Padding": "Padding1",
                "ParentReportNormID": 0,
                "ReportComponentName": "Nhóm chỉ số Tăng trưởng",
                "ReportComponentNameEn": "Growth rates",
                "Unit": "%",
                "UnitEn": "%",
                "OrderType": null,
                "OrderingComponent": null,
                "RowNumber": null,
                "ReportComponentTypeID": 1,
                "ChildTotal": 0,
                "Levels": 0,
                "Value1": 0.0,
                "Value2": 0.0,
                "Value3": 11.11,
                "Value4": 0.0,
                "Vl": null,
                "IsShowData": true
            },
            {
                "ID": 18,
                "ReportNormID": 72,
                "Name": "Tăng trưởng dư nợ cho vay",
                "NameEn": "Deposits from customers",
                "NameMobile": "Tăng trưởng dư nợ cho vay",
                "NameMobileEn": "Deposits from customers",
                "CssStyle": "",
                "Padding": "Padding1",
                "ParentReportNormID": 0,
                "ReportComponentName": "Nhóm chỉ số Tăng trưởng",
                "ReportComponentNameEn": "Growth rates",
                "Unit": "%",
                "UnitEn": "%",
                "OrderType": null,
                "OrderingComponent": null,
                "RowNumber": null,
                "ReportComponentTypeID": 1,
                "ChildTotal": 0,
                "Levels": 0,
                "Value1": -2.26,
                "Value2": 4.74,
                "Value3": 15.11,
                "Value4": 14.83,
                "Vl": null,
                "IsShowData": true
            },
            {
                "ID": 19,
                "ReportNormID": 111,
                "Name": "Tăng trưởng huy động vốn khách hàng",
                "NameEn": "Deposits from customers",
                "NameMobile": "Tăng trưởng huy động vốn khách hàng",
                "NameMobileEn": "Deposits from customers",
                "CssStyle": "",
                "Padding": "Padding1",
                "ParentReportNormID": 0,
                "ReportComponentName": "Nhóm chỉ số Tăng trưởng",
                "ReportComponentNameEn": "Growth rates",
                "Unit": "%",
                "UnitEn": "%",
                "OrderType": null,
                "OrderingComponent": null,
                "RowNumber": null,
                "ReportComponentTypeID": 1,
                "ChildTotal": 0,
                "Levels": 0,
                "Value1": 18.94,
                "Value2": 28.15,
                "Value3": 40.83,
                "Value4": 14.79,
                "Vl": null,
                "IsShowData": true
            },
            {
                "ID": 20,
                "ReportNormID": 112,
                "Name": "Tăng trưởng thu nhập lãi thuần",
                "NameEn": "Net interest income",
                "NameMobile": "Tăng trưởng thu nhập lãi thuần",
                "NameMobileEn": "Net interest income",
                "CssStyle": "",
                "Padding": "Padding1",
                "ParentReportNormID": 0,
                "ReportComponentName": "Nhóm chỉ số Tăng trưởng",
                "ReportComponentNameEn": "Growth rates",
                "Unit": "%",
                "UnitEn": "%",
                "OrderType": null,
                "OrderingComponent": null,
                "RowNumber": null,
                "ReportComponentTypeID": 1,
                "ChildTotal": 0,
                "Levels": 0,
                "Value1": -33.4,
                "Value2": -10.7,
                "Value3": 1.11,
                "Value4": 79.55,
                "Vl": null,
                "IsShowData": true
            },
            {
                "ID": 21,
                "ReportNormID": 113,
                "Name": "Tăng trưởng dự phòng rủi ro tín dụng",
                "NameEn": "Provisions for loan losses",
                "NameMobile": "Tăng trưởng dự phòng rủi ro tín dụng",
                "NameMobileEn": "Provisions for loan losses",
                "CssStyle": "",
                "Padding": "Padding1",
                "ParentReportNormID": 0,
                "ReportComponentName": "Nhóm chỉ số Tăng trưởng",
                "ReportComponentNameEn": "Growth rates",
                "Unit": "%",
                "UnitEn": "%",
                "OrderType": null,
                "OrderingComponent": null,
                "RowNumber": null,
                "ReportComponentTypeID": 1,
                "ChildTotal": 0,
                "Levels": 0,
                "Value1": 6.34,
                "Value2": -0.62,
                "Value3": 36.17,
                "Value4": 47.98,
                "Vl": null,
                "IsShowData": true
            },
            {
                "ID": 22,
                "ReportNormID": 114,
                "Name": "Tăng trưởng thu phí dịch vụ thuần",
                "NameEn": "Net fee and commission income",
                "NameMobile": "Tăng trưởng thu phí dịch vụ thuần",
                "NameMobileEn": "Net fee and commission income",
                "CssStyle": "",
                "Padding": "Padding1",
                "ParentReportNormID": 0,
                "ReportComponentName": "Nhóm chỉ số Tăng trưởng",
                "ReportComponentNameEn": "Growth rates",
                "Unit": "%",
                "UnitEn": "%",
                "OrderType": null,
                "OrderingComponent": null,
                "RowNumber": null,
                "ReportComponentTypeID": 1,
                "ChildTotal": 0,
                "Levels": 0,
                "Value1": 22.45,
                "Value2": 2.19,
                "Value3": 6.92,
                "Value4": 12.64,
                "Vl": null,
                "IsShowData": true
            },
            {
                "ID": 23,
                "ReportNormID": 115,
                "Name": "Tăng trưởng tổng thu nhập HĐKD trước dự phòng",
                "NameEn": "Operating profit before provision for credit losses",
                "NameMobile": "Tăng trưởng tổng thu nhập HĐKD trước dự phòng",
                "NameMobileEn": "Operating profit before provision for credit losses",
                "CssStyle": "",
                "Padding": "Padding1",
                "ParentReportNormID": 0,
                "ReportComponentName": "Nhóm chỉ số Tăng trưởng",
                "ReportComponentNameEn": "Growth rates",
                "Unit": "%",
                "UnitEn": "%",
                "OrderType": null,
                "OrderingComponent": null,
                "RowNumber": null,
                "ReportComponentTypeID": 1,
                "ChildTotal": 0,
                "Levels": 0,
                "Value1": -39.14,
                "Value2": -29.8,
                "Value3": -9.2,
                "Value4": 55.56,
                "Vl": null,
                "IsShowData": true
            },
            {
                "ID": 24,
                "ReportNormID": 116,
                "Name": "Tăng trưởng tổng chi phí HĐKD",
                "NameEn": "Operating expenses",
                "NameMobile": "Tăng trưởng tổng chi phí HĐKD",
                "NameMobileEn": "Operating expenses",
                "CssStyle": "",
                "Padding": "Padding1",
                "ParentReportNormID": 0,
                "ReportComponentName": "Nhóm chỉ số Tăng trưởng",
                "ReportComponentNameEn": "Growth rates",
                "Unit": "%",
                "UnitEn": "%",
                "OrderType": null,
                "OrderingComponent": null,
                "RowNumber": null,
                "ReportComponentTypeID": 1,
                "ChildTotal": 0,
                "Levels": 0,
                "Value1": 1.35,
                "Value2": 12.48,
                "Value3": 6.07,
                "Value4": 39.01,
                "Vl": null,
                "IsShowData": true
            }
        ],
        "Liquidity ratios": [
            {
                "ID": 25,
                "ReportNormID": 80,
                "Name": "Dư nợ cho vay khách hàng/Tổng vốn huy động (LDR)",
                "NameEn": "Outstanding loans/Customer deposits",
                "NameMobile": "Dư nợ cho vay khách hàng/Tổng vốn huy động (LDR)",
                "NameMobileEn": "Outstanding loans/Customer deposits",
                "CssStyle": "",
                "Padding": "Padding1",
                "ParentReportNormID": 0,
                "ReportComponentName": "Nhóm chỉ số Thanh khoản",
                "ReportComponentNameEn": "Liquidity ratios",
                "Unit": "%",
                "UnitEn": "%",
                "OrderType": null,
                "OrderingComponent": null,
                "RowNumber": null,
                "ReportComponentTypeID": 3,
                "ChildTotal": 0,
                "Levels": 0,
                "Value1": 64.85,
                "Value2": 78.68,
                "Value3": 82.1,
                "Value4": 92.62,
                "Vl": null,
                "IsShowData": true
            },
            {
                "ID": 26,
                "ReportNormID": 81,
                "Name": "Dư nợ cho vay/Tổng tài sản Có",
                "NameEn": "Outstanding loans/Total assets",
                "NameMobile": "Dư nợ cho vay/Tổng tài sản Có",
                "NameMobileEn": "Outstanding loans/Total assets",
                "CssStyle": "",
                "Padding": "Padding1",
                "ParentReportNormID": 0,
                "ReportComponentName": "Nhóm chỉ số Thanh khoản",
                "ReportComponentNameEn": "Liquidity ratios",
                "Unit": "%",
                "UnitEn": "%",
                "OrderType": null,
                "OrderingComponent": null,
                "RowNumber": null,
                "ReportComponentTypeID": 3,
                "ChildTotal": 0,
                "Levels": 0,
                "Value1": 59.52,
                "Value2": 70.81,
                "Value3": 73.11,
                "Value4": 67.13,
                "Vl": null,
                "IsShowData": true
            },
            {
                "ID": 27,
                "ReportNormID": 119,
                "Name": "Vốn chủ sở hữu/Tổng vốn huy động ",
                "NameEn": "Equity/Deposits from customers",
                "NameMobile": "Vốn chủ sở hữu/Tổng vốn huy động ",
                "NameMobileEn": "Equity/Deposits from customers",
                "CssStyle": "",
                "Padding": "Padding1",
                "ParentReportNormID": 0,
                "ReportComponentName": "Nhóm chỉ số Thanh khoản",
                "ReportComponentNameEn": "Liquidity ratios",
                "Unit": "%",
                "UnitEn": "%",
                "OrderType": null,
                "OrderingComponent": null,
                "RowNumber": null,
                "ReportComponentTypeID": 3,
                "ChildTotal": 0,
                "Levels": 0,
                "Value1": 0.0,
                "Value2": 8.84,
                "Value3": 10.01,
                "Value4": 0.12,
                "Vl": null,
                "IsShowData": true
            },
            {
                "ID": 28,
                "ReportNormID": 120,
                "Name": "Vốn chủ sở hữu/Tổng tài sản Có",
                "NameEn": "Equity/Total assets",
                "NameMobile": "Vốn chủ sở hữu/Tổng tài sản Có",
                "NameMobileEn": "Equity/Total assets",
                "CssStyle": "",
                "Padding": "Padding1",
                "ParentReportNormID": 0,
                "ReportComponentName": "Nhóm chỉ số Thanh khoản",
                "ReportComponentNameEn": "Liquidity ratios",
                "Unit": "%",
                "UnitEn": "%",
                "OrderType": null,
                "OrderingComponent": null,
                "RowNumber": null,
                "ReportComponentTypeID": 3,
                "ChildTotal": 0,
                "Levels": 0,
                "Value1": 6.48,
                "Value2": 7.86,
                "Value3": 8.81,
                "Value4": 8.87,
                "Vl": null,
                "IsShowData": true
            }
        ],
        "Asset quality ratios": [
            {
                "ID": 29,
                "ReportNormID": 117,
                "Name": "Dự phòng rủi ro tín dụng/Tổng dư nợ",
                "NameEn": "Loan loss provision ratio",
                "NameMobile": "Dự phòng rủi ro tín dụng/Tổng dư nợ",
                "NameMobileEn": "Loan loss provision ratio",
                "CssStyle": "",
                "Padding": "Padding1",
                "ParentReportNormID": 0,
                "ReportComponentName": "Nhóm chỉ số Chất lượng tài sản",
                "ReportComponentNameEn": "Asset quality ratios",
                "Unit": "%",
                "UnitEn": "%",
                "OrderType": null,
                "OrderingComponent": null,
                "RowNumber": null,
                "ReportComponentTypeID": 13,
                "ChildTotal": 0,
                "Levels": 0,
                "Value1": -35.3,
                "Value2": -2.73,
                "Value3": -1.55,
                "Value4": -0.7,
                "Vl": null,
                "IsShowData": true
            },
            {
                "ID": 30,
                "ReportNormID": 118,
                "Name": "Tài sản Có sinh lãi/Tổng tài sản Có",
                "NameEn": "Earning assets/Total assets",
                "NameMobile": "Tài sản Có sinh lãi/Tổng tài sản Có",
                "NameMobileEn": "Earning assets/Total assets",
                "CssStyle": "",
                "Padding": "Padding1",
                "ParentReportNormID": 0,
                "ReportComponentName": "Nhóm chỉ số Chất lượng tài sản",
                "ReportComponentNameEn": "Asset quality ratios",
                "Unit": "%",
                "UnitEn": "%",
                "OrderType": null,
                "OrderingComponent": null,
                "RowNumber": null,
                "ReportComponentTypeID": 13,
                "ChildTotal": 0,
                "Levels": 0,
                "Value1": 82.99,
                "Value2": 85.33,
                "Value3": 85.88,
                "Value4": 79.74,
                "Vl": null,
                "IsShowData": true
            }
        ]
    },
    [],
    []
]