[
    [
        {
            "ID": 4,
            "Row": 4,
            "CompanyID": 1279,
            "YearPeriod": 2009,
            "TermCode": "N",
            "TermName": "Năm",
            "TermNameEN": "Year",
            "ReportTermID": 1,
            "DisplayOrdering": 1,
            "United": "ĐL",
            "AuditedStatus": "KT",
            "PeriodBegin": "200901",
            "PeriodEnd": "200912",
            "TotalRow": 9,
            "BusinessType": 4,
            "ReportNote": null,
            "ReportNoteEn": null
        },
        {
            "ID": 3,
            "Row": 3,
            "CompanyID": 1279,
            "YearPeriod": 2010,
            "TermCode": "N",
            "TermName": "Năm",
            "TermNameEN": "Year",
            "ReportTermID": 1,
            "DisplayOrdering": 1,
            "United": "ĐL",
            "AuditedStatus": "KT",
            "PeriodBegin": "201001",
            "PeriodEnd": "201012",
            "TotalRow": 9,
            "BusinessType": 4,
            "ReportNote": null,
            "ReportNoteEn": null
        },
        {
            "ID": 2,
            "Row": 2,
            "CompanyID": 1279,
            "YearPeriod": 2011,
            "TermCode": "N",
            "TermName": "Năm",
            "TermNameEN": "Year",
            "ReportTermID": 1,
            "DisplayOrdering": 1,
            "United": "ĐL",
            "AuditedStatus": "KT",
            "PeriodBegin": "201101",
            "PeriodEnd": "201112",
            "TotalRow": 9,
            "BusinessType": 4,
            "ReportNote": null,
            "ReportNoteEn": null
        },
        {
            "ID": 1,
            "Row": 1,
            "CompanyID": 1279,
            "YearPeriod": 2012,
            "TermCode": "N",
            "TermName": "Năm",
            "TermNameEN": "Year",
            "ReportTermID": 1,
            "DisplayOrdering": 1,
            "United": "ĐL",
            "AuditedStatus": "KT",
            "PeriodBegin": "201201",
            "PeriodEnd": "201212",
            "TotalRow": 9,
            "BusinessType": 4,
            "ReportNote": null,
            "ReportNoteEn": null
        }
    ],
    {
        "Balance Sheet": [
            {
                "ID": 1,
                "ReportNormID": 3414,
                "Name": "A. TÀI SẢN",
                "NameEn": "ASSETS",
                "NameMobile": "A. TÀI SẢN",
                "NameMobileEn": "ASSETS",
                "CssStyle": "MaxB",
                "Padding": "Padding1",
                "ParentReportNormID": 3414,
                "ReportComponentName": "Cân đối kế toán",
                "ReportComponentNameEn": "Balance Sheet",
                "Unit": null,
                "UnitEn": null,
                "OrderType": null,
                "OrderingComponent": null,
                "RowNumber": null,
                "ReportComponentTypeID": null,
                "ChildTotal": 0,
                "Levels": 0,
                "Value1": 0.0,
                "Value2": 0.0,
                "Value3": null,
                "Value4": null,
                "Vl": null,
                "IsShowData": true
            },
            {
                "ID": 2,
                "ReportNormID": 3423,
                "Name": "1. Tiền gửi ngân hàng",
                "NameEn": "1. Cash in bank",
                "NameMobile": "1. Tiền gửi ngân hàng",
                "NameMobileEn": "1. Cash in bank",
                "CssStyle": "Normal",
                "Padding": "Padding3",
                "ParentReportNormID": 3415,
                "ReportComponentName": "Cân đối kế toán",
                "ReportComponentNameEn": "Balance Sheet",
                "Unit": null,
                "UnitEn": null,
                "OrderType": null,
                "OrderingComponent": null,
                "RowNumber": null,
                "ReportComponentTypeID": null,
                "ChildTotal": 0,
                "Levels": 1,
                "Value1": 136388.0,
                "Value2": 183786.0,
                "Value3": 142814.0,
                "Value4": 146471.0,
                "Vl": null,
                "IsShowData": true
            },
            {
                "ID": 3,
                "ReportNormID": 3418,
                "Name": "2. Đầu tư chứng khoán",
                "NameEn": "2. Investments in securities ",
                "NameMobile": "2. Đầu tư chứng khoán",
                "NameMobileEn": "2. Investments in securities ",
                "CssStyle": "Normal",
                "Padding": "Padding3",
                "ParentReportNormID": 3415,
                "ReportComponentName": "Cân đối kế toán",
                "ReportComponentNameEn": "Balance Sheet",
                "Unit": null,
                "UnitEn": null,
                "OrderType": null,
                "OrderingComponent": null,
                "RowNumber": null,
                "ReportComponentTypeID": null,
                "ChildTotal": 0,
                "Levels": 1,
                "Value1": 1205172.0,
                "Value2": 1077061.0,
                "Value3": 1976976.0,
                "Value4": 2266373.0,
                "Vl": null,
                "IsShowData": true
            },
            {
                "ID": 4,
                "ReportNormID": 3419,
                "Name": "3. Đầu tư khác",
                "NameEn": "3. Other investments",
                "NameMobile": "3. Đầu tư khác",
                "NameMobileEn": "3. Other investments",
                "CssStyle": "Normal",
                "Padding": "Padding3",
                "ParentReportNormID": 3415,
                "ReportComponentName": "Cân đối kế toán",
                "ReportComponentNameEn": "Balance Sheet",
                "Unit": null,
                "UnitEn": null,
                "OrderType": null,
                "OrderingComponent": null,
                "RowNumber": null,
                "ReportComponentTypeID": null,
                "ChildTotal": 0,
                "Levels": 1,
                "Value1": 180000.0,
                "Value2": 0.0,
                "Value3": 0.0,
                "Value4": 81500.0,
                "Vl": null,
                "IsShowData": true
            },
            {
                "ID": 5,
                "ReportNormID": 3420,
                "Name": "4. Phải thu hoạt động đầu tư",
                "NameEn": "4. Receivables from securities trading",
                "NameMobile": "4. Phải thu hoạt động đầu tư",
                "NameMobileEn": "4. Receivables from securities trading",
                "CssStyle": "Normal",
                "Padding": "Padding3",
                "ParentReportNormID": 3415,
                "ReportComponentName": "Cân đối kế toán",
                "ReportComponentNameEn": "Balance Sheet",
                "Unit": null,
                "UnitEn": null,
                "OrderType": null,
                "OrderingComponent": null,
                "RowNumber": null,
                "ReportComponentTypeID": null,
                "ChildTotal": 0,
                "Levels": 1,
                "Value1": 1145.0,
                "Value2": 59395.0,
                "Value3": 2081.0,
                "Value4": 17790.0,
                "Vl": null,
                "IsShowData": true
            },
            {
                "ID": 6,
                "ReportNormID": 3424,
                "Name": "5. Phải thu khác",
                "NameEn": "5. Other receivables",
                "NameMobile": "5. Phải thu khác",
                "NameMobileEn": "5. Other receivables",
                "CssStyle": "Normal",
                "Padding": "Padding3",
                "ParentReportNormID": 3415,
                "ReportComponentName": "Cân đối kế toán",
                "ReportComponentNameEn": "Balance Sheet",
                "Unit": null,
                "UnitEn": null,
                "OrderType": null,
                "OrderingComponent": null,
                "RowNumber": null,
                "ReportComponentTypeID": null,
                "ChildTotal": 0,
                "Levels": 1,
                "Value1": 6248.0,
                "Value2": 7031.0,
                "Value3": 16726.0,
                "Value4": 15896.0,
                "Vl": null,
                "IsShowData": true
            },
            {
                "ID": 7,
                "ReportNormID": 3415,
                "Name": "TỔNG TÀI SẢN",
                "NameEn": "TOTAL ASSETS",
                "NameMobile": "TỔNG TÀI SẢN",
                "NameMobileEn": "TOTAL ASSETS",
                "CssStyle": "LargeB",
                "Padding": "Padding1",
                "ParentReportNormID": 3415,
                "ReportComponentName": "Cân đối kế toán",
                "ReportComponentNameEn": "Balance Sheet",
                "Unit": null,
                "UnitEn": null,
                "OrderType": null,
                "OrderingComponent": null,
                "RowNumber": null,
                "ReportComponentTypeID": null,
                "ChildTotal": 5,
                "Levels": 0,
                "Value1": 1528953.0,
                "Value2": 1327274.0,
                "Value3": 2138596.0,
                "Value4": 2528031.0,
                "Vl": null,
                "IsShowData": false
            },
            {
                "ID": 8,
                "ReportNormID": 3413,
                "Name": "B. NGUỒN VỐN",
                "NameEn": "B. OWNER'S EQUITY ",
                "NameMobile": "B. NGUỒN VỐN",
                "NameMobileEn": "B. OWNER'S EQUITY ",
                "CssStyle": "MaxB",
                "Padding": "Padding1",
                "ParentReportNormID": 3413,
                "ReportComponentName": "Cân đối kế toán",
                "ReportComponentNameEn": "Balance Sheet",
                "Unit": null,
                "UnitEn": null,
                "OrderType": null,
                "OrderingComponent": null,
                "RowNumber": null,
                "ReportComponentTypeID": null,
                "ChildTotal": 0,
                "Levels": 0,
                "Value1": 0.0,
                "Value2": 0.0,
                "Value3": null,
                "Value4": null,
                "Vl": null,
                "IsShowData": true
            },
            {
                "ID": 9,
                "ReportNormID": 3416,
                "Name": "I. Nợ phải trả",
                "NameEn": "I. Liabilities",
                "NameMobile": "I. Nợ phải trả",
                "NameMobileEn": "I. Liabilities",
                "CssStyle": "NormalB",
                "Padding": "Padding2",
                "ParentReportNormID": 3417,
                "ReportComponentName": "Cân đối kế toán",
                "ReportComponentNameEn": "Balance Sheet",
                "Unit": null,
                "UnitEn": null,
                "OrderType": null,
                "OrderingComponent": null,
                "RowNumber": null,
                "ReportComponentTypeID": null,
                "ChildTotal": 6,
                "Levels": 1,
                "Value1": 8901.0,
                "Value2": 28938.0,
                "Value3": 12328.0,
                "Value4": 48160.0,
                "Vl": null,
                "IsShowData": true
            },
            {
                "ID": 10,
                "ReportNormID": 3425,
                "Name": "1. Vay ngắn hạn",
                "NameEn": "1. Short-term loans",
                "NameMobile": "1. Vay ngắn hạn",
                "NameMobileEn": "1. Short-term loans",
                "CssStyle": "Normal",
                "Padding": "Padding3",
                "ParentReportNormID": 3416,
                "ReportComponentName": "Cân đối kế toán",
                "ReportComponentNameEn": "Balance Sheet",
                "Unit": null,
                "UnitEn": null,
                "OrderType": null,
                "OrderingComponent": null,
                "RowNumber": null,
                "ReportComponentTypeID": null,
                "ChildTotal": 0,
                "Levels": 2,
                "Value1": 0.0,
                "Value2": 0.0,
                "Value3": 0.0,
                "Value4": 0.0,
                "Vl": null,
                "IsShowData": true
            },
            {
                "ID": 11,
                "ReportNormID": 3426,
                "Name": "2. Phải trả hoạt động đầu tư (kinh doanh chứng khoán)",
                "NameEn": "2. Payables for investment activities",
                "NameMobile": "2. Phải trả hoạt động đầu tư (kinh doanh chứng khoán)",
                "NameMobileEn": "2. Payables for investment activities",
                "CssStyle": "Normal",
                "Padding": "Padding3",
                "ParentReportNormID": 3416,
                "ReportComponentName": "Cân đối kế toán",
                "ReportComponentNameEn": "Balance Sheet",
                "Unit": null,
                "UnitEn": null,
                "OrderType": null,
                "OrderingComponent": null,
                "RowNumber": null,
                "ReportComponentTypeID": null,
                "ChildTotal": 0,
                "Levels": 2,
                "Value1": 5193.0,
                "Value2": 25296.0,
                "Value3": 7185.0,
                "Value4": 38037.0,
                "Vl": null,
                "IsShowData": true
            },
            {
                "ID": 12,
                "ReportNormID": 3427,
                "Name": "3. Phải trả thu nhập cho Nhà đầu tư",
                "NameEn": "3. Income payables for investors",
                "NameMobile": "3. Phải trả thu nhập cho Nhà đầu tư",
                "NameMobileEn": "3. Income payables for investors",
                "CssStyle": "Normal",
                "Padding": "Padding3",
                "ParentReportNormID": 3416,
                "ReportComponentName": "Cân đối kế toán",
                "ReportComponentNameEn": "Balance Sheet",
                "Unit": null,
                "UnitEn": null,
                "OrderType": null,
                "OrderingComponent": null,
                "RowNumber": null,
                "ReportComponentTypeID": null,
                "ChildTotal": 0,
                "Levels": 2,
                "Value1": 40.0,
                "Value2": 0.0,
                "Value3": 0.0,
                "Value4": 0.0,
                "Vl": null,
                "IsShowData": true
            },
            {
                "ID": 13,
                "ReportNormID": 3428,
                "Name": "4. Phải trả phụ cấp Ban đại diện Quỹ",
                "NameEn": "4. Remunerations payables to the Board of Representative",
                "NameMobile": "4. Phải trả phụ cấp Ban đại diện Quỹ",
                "NameMobileEn": "4. Remunerations payables to the Board of Representative",
                "CssStyle": "Normal",
                "Padding": "Padding3",
                "ParentReportNormID": 3416,
                "ReportComponentName": "Cân đối kế toán",
                "ReportComponentNameEn": "Balance Sheet",
                "Unit": null,
                "UnitEn": null,
                "OrderType": null,
                "OrderingComponent": null,
                "RowNumber": null,
                "ReportComponentTypeID": null,
                "ChildTotal": 0,
                "Levels": 2,
                "Value1": 92.0,
                "Value2": 92.0,
                "Value3": 92.0,
                "Value4": 92.0,
                "Vl": null,
                "IsShowData": true
            },
            {
                "ID": 14,
                "ReportNormID": 3429,
                "Name": "5. Phải trả cho Công ty quản lý Quỹ, NH giám sát",
                "NameEn": "5. Payables to the fund manager and the custodian bank",
                "NameMobile": "5. Phải trả cho Công ty quản lý Quỹ, NH giám sát",
                "NameMobileEn": "5. Payables to the fund manager and the custodian bank",
                "CssStyle": "Normal",
                "Padding": "Padding3",
                "ParentReportNormID": 3416,
                "ReportComponentName": "Cân đối kế toán",
                "ReportComponentNameEn": "Balance Sheet",
                "Unit": null,
                "UnitEn": null,
                "OrderType": null,
                "OrderingComponent": null,
                "RowNumber": null,
                "ReportComponentTypeID": null,
                "ChildTotal": 0,
                "Levels": 2,
                "Value1": 2642.0,
                "Value2": 2257.0,
                "Value3": 3706.0,
                "Value4": 4313.0,
                "Vl": null,
                "IsShowData": true
            },
            {
                "ID": 15,
                "ReportNormID": 3430,
                "Name": "6. Phải trả khác",
                "NameEn": "6. Other payables",
                "NameMobile": "6. Phải trả khác",
                "NameMobileEn": "6. Other payables",
                "CssStyle": "Normal",
                "Padding": "Padding3",
                "ParentReportNormID": 3416,
                "ReportComponentName": "Cân đối kế toán",
                "ReportComponentNameEn": "Balance Sheet",
                "Unit": null,
                "UnitEn": null,
                "OrderType": null,
                "OrderingComponent": null,
                "RowNumber": null,
                "ReportComponentTypeID": null,
                "ChildTotal": 0,
                "Levels": 2,
                "Value1": 934.0,
                "Value2": 1293.0,
                "Value3": 1345.0,
                "Value4": 5718.0,
                "Vl": null,
                "IsShowData": true
            },
            {
                "ID": 16,
                "ReportNormID": 4074,
                "Name": "II. Nguồn vốn chủ sở hữu",
                "NameEn": "II. Owner's equity",
                "NameMobile": "II. Nguồn vốn chủ sở hữu",
                "NameMobileEn": "II. Owner's equity",
                "CssStyle": "NormalB",
                "Padding": "Padding2",
                "ParentReportNormID": 3417,
                "ReportComponentName": "Cân đối kế toán",
                "ReportComponentNameEn": "Balance Sheet",
                "Unit": null,
                "UnitEn": null,
                "OrderType": null,
                "OrderingComponent": null,
                "RowNumber": null,
                "ReportComponentTypeID": null,
                "ChildTotal": 4,
                "Levels": 1,
                "Value1": 1520053.0,
                "Value2": 1298336.0,
                "Value3": 2126268.0,
                "Value4": 2479871.0,
                "Vl": null,
                "IsShowData": true
            },
            {
                "ID": 17,
                "ReportNormID": 3431,
                "Name": "1. Vốn góp của các nhà đầu tư",
                "NameEn": "1. Capital contributed by investors",
                "NameMobile": "1. Vốn góp của các nhà đầu tư",
                "NameMobileEn": "1. Capital contributed by investors",
                "CssStyle": "Normal",
                "Padding": "Padding3",
                "ParentReportNormID": 4074,
                "ReportComponentName": "Cân đối kế toán",
                "ReportComponentNameEn": "Balance Sheet",
                "Unit": null,
                "UnitEn": null,
                "OrderType": null,
                "OrderingComponent": null,
                "RowNumber": null,
                "ReportComponentTypeID": null,
                "ChildTotal": 2,
                "Levels": 2,
                "Value1": 2224171.0,
                "Value2": 2224171.0,
                "Value3": 2224171.0,
                "Value4": 2224171.0,
                "Vl": null,
                "IsShowData": true
            },
            {
                "ID": 18,
                "ReportNormID": 3436,
                "Name": "1.1. Vốn góp",
                "NameEn": "1.1. Capital contributed",
                "NameMobile": "1.1. Vốn góp",
                "NameMobileEn": "1.1. Capital contributed",
                "CssStyle": "NormalI",
                "Padding": "Padding5",
                "ParentReportNormID": 3431,
                "ReportComponentName": "Cân đối kế toán",
                "ReportComponentNameEn": "Balance Sheet",
                "Unit": null,
                "UnitEn": null,
                "OrderType": null,
                "OrderingComponent": null,
                "RowNumber": null,
                "ReportComponentTypeID": null,
                "ChildTotal": 0,
                "Levels": 3,
                "Value1": 1000000.0,
                "Value2": 1000000.0,
                "Value3": 1000000.0,
                "Value4": 1000000.0,
                "Vl": null,
                "IsShowData": true
            },
            {
                "ID": 19,
                "ReportNormID": 3422,
                "Name": "1.2. Thặng dư vốn",
                "NameEn": "1.2. Capital surplus",
                "NameMobile": "1.2. Thặng dư vốn",
                "NameMobileEn": "1.2. Capital surplus",
                "CssStyle": "NormalI",
                "Padding": "Padding5",
                "ParentReportNormID": 3431,
                "ReportComponentName": "Cân đối kế toán",
                "ReportComponentNameEn": "Balance Sheet",
                "Unit": null,
                "UnitEn": null,
                "OrderType": null,
                "OrderingComponent": null,
                "RowNumber": null,
                "ReportComponentTypeID": null,
                "ChildTotal": 0,
                "Levels": 3,
                "Value1": 1224171.0,
                "Value2": 1224171.0,
                "Value3": 1224171.0,
                "Value4": 1224171.0,
                "Vl": null,
                "IsShowData": true
            },
            {
                "ID": 20,
                "ReportNormID": 3432,
                "Name": "2. Kết quả hoạt động chưa phân phối",
                "NameEn": "2. Undistributed earnings",
                "NameMobile": "2. Kết quả hoạt động chưa phân phối",
                "NameMobileEn": "2. Undistributed earnings",
                "CssStyle": "Normal",
                "Padding": "Padding3",
                "ParentReportNormID": 4074,
                "ReportComponentName": "Cân đối kế toán",
                "ReportComponentNameEn": "Balance Sheet",
                "Unit": null,
                "UnitEn": null,
                "OrderType": null,
                "OrderingComponent": null,
                "RowNumber": null,
                "ReportComponentTypeID": null,
                "ChildTotal": 0,
                "Levels": 2,
                "Value1": -704118.0,
                "Value2": -925835.0,
                "Value3": -97903.0,
                "Value4": 255700.0,
                "Vl": null,
                "IsShowData": true
            },
            {
                "ID": 21,
                "ReportNormID": 3417,
                "Name": "TỔNG CỘNG NGUỒN VỐN",
                "NameEn": "TOTAL LIABILITIES AND OWNER'S EQUITY",
                "NameMobile": "TỔNG CỘNG NGUỒN VỐN",
                "NameMobileEn": "TOTAL LIABILITIES AND OWNER'S EQUITY",
                "CssStyle": "LargeB",
                "Padding": "Padding1",
                "ParentReportNormID": 3417,
                "ReportComponentName": "Cân đối kế toán",
                "ReportComponentNameEn": "Balance Sheet",
                "Unit": null,
                "UnitEn": null,
                "OrderType": null,
                "OrderingComponent": null,
                "RowNumber": null,
                "ReportComponentTypeID": null,
                "ChildTotal": 12,
                "Levels": 0,
                "Value1": 1528953.0,
                "Value2": 1327274.0,
                "Value3": 2138596.0,
                "Value4": 2528031.0,
                "Vl": null,
                "IsShowData": false
            }
        ]
    },
    [
        {
            "AuditedStatusCode": "SX",
            "Description": "Soát xét",
            "DescriptionEn": "Reviewed"
        },
        {
            "AuditedStatusCode": "CKT",
            "Description": "Chưa kiểm toán",
            "DescriptionEn": "Unaudited"
        },
        {
            "AuditedStatusCode": "KT",
            "Description": "Kiểm toán",
            "DescriptionEn": "Audited"
        }
    ],
    [
        {
            "UnitedCode": "HN",
            "UnitedName": "Hợp nhất",
            "UnitedNameEN": "Consolidated"
        },
        {
            "UnitedCode": "ĐL",
            "UnitedName": "Đơn lẻ",
            "UnitedNameEN": "Stand-alone"
        },
        {
            "UnitedCode": "CTM",
            "UnitedName": "Công ty mẹ",
            "UnitedNameEN": "Parent Company"
        }
    ]
]