[
    [
        {
            "ID": 4,
            "Row": 4,
            "CompanyID": 1186,
            "YearPeriod": 2016,
            "TermCode": "N",
            "TermName": "Năm",
            "TermNameEN": "Year",
            "ReportTermID": 1,
            "DisplayOrdering": 1,
            "United": "HN",
            "AuditedStatus": "KT",
            "PeriodBegin": "201601",
            "PeriodEnd": "201612",
            "TotalRow": 12,
            "BusinessType": 2,
            "ReportNote": null,
            "ReportNoteEn": null
        },
        {
            "ID": 3,
            "Row": 3,
            "CompanyID": 1186,
            "YearPeriod": 2017,
            "TermCode": "N",
            "TermName": "Năm",
            "TermNameEN": "Year",
            "ReportTermID": 1,
            "DisplayOrdering": 1,
            "United": "HN",
            "AuditedStatus": "KT",
            "PeriodBegin": "201701",
            "PeriodEnd": "201712",
            "TotalRow": 12,
            "BusinessType": 2,
            "ReportNote": null,
            "ReportNoteEn": null
        },
        {
            "ID": 2,
            "Row": 2,
            "CompanyID": 1186,
            "YearPeriod": 2018,
            "TermCode": "N",
            "TermName": "Năm",
            "TermNameEN": "Year",
            "ReportTermID": 1,
            "DisplayOrdering": 1,
            "United": "ĐL",
            "AuditedStatus": "KT",
            "PeriodBegin": "201801",
            "PeriodEnd": "201812",
            "TotalRow": 12,
            "BusinessType": 2,
            "ReportNote": null,
            "ReportNoteEn": null
        },
        {
            "ID": 1,
            "Row": 1,
            "CompanyID": 1186,
            "YearPeriod": 2019,
            "TermCode": "N",
            "TermName": "Năm",
            "TermNameEN": "Year",
            "ReportTermID": 1,
            "DisplayOrdering": 1,
            "United": "ĐL",
            "AuditedStatus": "KT",
            "PeriodBegin": "201901",
            "PeriodEnd": "201912",
            "TotalRow": 12,
            "BusinessType": 2,
            "ReportNote": null,
            "ReportNoteEn": null
        }
    ],
    {
        "Income Statement": [
            {
                "ID": 1,
                "ReportNormID": 4590,
                "Name": "Doanh thu thuần về hoạt động kinh doanh",
                "NameEn": "Net revenue",
                "NameMobile": "DT Thuần HĐKD",
                "NameMobileEn": "NR",
                "CssStyle": "NormalB",
                "Padding": "Padding1",
                "ParentReportNormID": 4592,
                "ReportComponentName": "Kết quả kinh doanh",
                "ReportComponentNameEn": "Income Statement",
                "Unit": "",
                "UnitEn": "",
                "OrderType": 1,
                "OrderingComponent": 1,
                "RowNumber": 20,
                "ReportComponentTypeID": 12,
                "ChildTotal": 0,
                "Levels": 0,
                "Value1": 436975.0,
                "Value2": 452356.0,
                "Value3": 387671.0,
                "Value4": 187421.0,
                "Vl": null,
                "IsShowData": true
            },
            {
                "ID": 2,
                "ReportNormID": 4591,
                "Name": "Chi phí hoạt động kinh doanh",
                "NameEn": "Operating expenses",
                "NameMobile": "CP-HĐKD",
                "NameMobileEn": "GP",
                "CssStyle": "Normal",
                "Padding": "Padding1",
                "ParentReportNormID": 4581,
                "ReportComponentName": "Kết quả kinh doanh",
                "ReportComponentNameEn": "Income Statement",
                "Unit": "",
                "UnitEn": "",
                "OrderType": 1,
                "OrderingComponent": 1,
                "RowNumber": 21,
                "ReportComponentTypeID": 12,
                "ChildTotal": 0,
                "Levels": 0,
                "Value1": 236900.0,
                "Value2": 149280.0,
                "Value3": 214892.0,
                "Value4": 83189.0,
                "Vl": null,
                "IsShowData": true
            },
            {
                "ID": 3,
                "ReportNormID": 4592,
                "Name": "Lợi nhuận gộp của hoạt động kinh doanh",
                "NameEn": "Gross profit",
                "NameMobile": "LN Gộp HĐKD",
                "NameMobileEn": "GP",
                "CssStyle": "NormalB",
                "Padding": "Padding1",
                "ParentReportNormID": 4581,
                "ReportComponentName": "Kết quả kinh doanh",
                "ReportComponentNameEn": "Income Statement",
                "Unit": "",
                "UnitEn": "",
                "OrderType": 1,
                "OrderingComponent": 1,
                "RowNumber": 22,
                "ReportComponentTypeID": 12,
                "ChildTotal": 0,
                "Levels": 0,
                "Value1": 200075.0,
                "Value2": 303077.0,
                "Value3": 172779.0,
                "Value4": 104232.0,
                "Vl": null,
                "IsShowData": true
            },
            {
                "ID": 4,
                "ReportNormID": 4596,
                "Name": "Chi phí quản lý doanh nghiệp",
                "NameEn": "General and Administrative expenses",
                "NameMobile": "CP-QLDN",
                "NameMobileEn": "G&A",
                "CssStyle": "Normal",
                "Padding": "Padding1",
                "ParentReportNormID": 4581,
                "ReportComponentName": "Kết quả kinh doanh",
                "ReportComponentNameEn": "Income Statement",
                "Unit": "",
                "UnitEn": "",
                "OrderType": 1,
                "OrderingComponent": 1,
                "RowNumber": 23,
                "ReportComponentTypeID": 12,
                "ChildTotal": 0,
                "Levels": 0,
                "Value1": 19125.0,
                "Value2": 20961.0,
                "Value3": 24170.0,
                "Value4": 30360.0,
                "Vl": null,
                "IsShowData": true
            },
            {
                "ID": 5,
                "ReportNormID": 4581,
                "Name": "Lợi nhuận thuần từ hoạt động kinh doanh",
                "NameEn": "Operating profit",
                "NameMobile": "LN Thuần HĐKD",
                "NameMobileEn": "Operating profit",
                "CssStyle": "NormalB",
                "Padding": "Padding1",
                "ParentReportNormID": 4584,
                "ReportComponentName": "Kết quả kinh doanh",
                "ReportComponentNameEn": "Income Statement",
                "Unit": "",
                "UnitEn": "",
                "OrderType": 1,
                "OrderingComponent": 1,
                "RowNumber": 24,
                "ReportComponentTypeID": 12,
                "ChildTotal": 0,
                "Levels": 0,
                "Value1": 139498.0,
                "Value2": 257446.0,
                "Value3": 91976.0,
                "Value4": 64386.0,
                "Vl": null,
                "IsShowData": true
            },
            {
                "ID": 6,
                "ReportNormID": 4582,
                "Name": "Lợi nhuận khác",
                "NameEn": "Other profit",
                "NameMobile": "LN Khác",
                "NameMobileEn": "Other profit",
                "CssStyle": "Normal",
                "Padding": "Padding1",
                "ParentReportNormID": 4584,
                "ReportComponentName": "Kết quả kinh doanh",
                "ReportComponentNameEn": "Income Statement",
                "Unit": "",
                "UnitEn": "",
                "OrderType": 1,
                "OrderingComponent": 1,
                "RowNumber": 25,
                "ReportComponentTypeID": 12,
                "ChildTotal": 0,
                "Levels": 0,
                "Value1": 2678.0,
                "Value2": 10869.0,
                "Value3": 3684.0,
                "Value4": 621.0,
                "Vl": null,
                "IsShowData": true
            },
            {
                "ID": 7,
                "ReportNormID": 4583,
                "Name": "Phần lợi nhuận/lỗ từ công ty liên kết liên doanh",
                "NameEn": "Profit/Loss of investments in associates and joint ventures",
                "NameMobile": "LN Cty LKLD",
                "NameMobileEn": "P/L of inv. In AJV",
                "CssStyle": "Normal",
                "Padding": "Padding1",
                "ParentReportNormID": 4584,
                "ReportComponentName": "Kết quả kinh doanh",
                "ReportComponentNameEn": "Income Statement",
                "Unit": "",
                "UnitEn": "",
                "OrderType": 1,
                "OrderingComponent": 1,
                "RowNumber": 26,
                "ReportComponentTypeID": 12,
                "ChildTotal": 0,
                "Levels": 0,
                "Value1": null,
                "Value2": null,
                "Value3": null,
                "Value4": null,
                "Vl": null,
                "IsShowData": true
            },
            {
                "ID": 8,
                "ReportNormID": 4584,
                "Name": "Tổng lợi nhuận kế toán trước thuế",
                "NameEn": "Profit before tax",
                "NameMobile": "LNTT",
                "NameMobileEn": "PBT",
                "CssStyle": "NormalB",
                "Padding": "Padding1",
                "ParentReportNormID": 4585,
                "ReportComponentName": "Kết quả kinh doanh",
                "ReportComponentNameEn": "Income Statement",
                "Unit": "",
                "UnitEn": "",
                "OrderType": 1,
                "OrderingComponent": 1,
                "RowNumber": 27,
                "ReportComponentTypeID": 12,
                "ChildTotal": 0,
                "Levels": 0,
                "Value1": 142176.0,
                "Value2": 268315.0,
                "Value3": 95660.0,
                "Value4": 65007.0,
                "Vl": null,
                "IsShowData": true
            },
            {
                "ID": 9,
                "ReportNormID": 4585,
                "Name": "Lợi nhuận sau thuế TNDN",
                "NameEn": "Net profit after tax",
                "NameMobile": "LNST",
                "NameMobileEn": "Net PAT",
                "CssStyle": "NormalB",
                "Padding": "Padding1",
                "ParentReportNormID": 4587,
                "ReportComponentName": "Kết quả kinh doanh",
                "ReportComponentNameEn": "Income Statement",
                "Unit": "",
                "UnitEn": "",
                "OrderType": 1,
                "OrderingComponent": 1,
                "RowNumber": 28,
                "ReportComponentTypeID": 12,
                "ChildTotal": 0,
                "Levels": 0,
                "Value1": 116372.0,
                "Value2": 216556.0,
                "Value3": 78302.0,
                "Value4": 53740.0,
                "Vl": null,
                "IsShowData": true
            },
            {
                "ID": 10,
                "ReportNormID": 4587,
                "Name": "Lợi nhuận sau thuế của cổ đông Công ty mẹ",
                "NameEn": "Profit after tax for shareholders of parent company",
                "NameMobile": "LNST của CĐ CTM",
                "NameMobileEn": "PAT for SPC",
                "CssStyle": "NormalB",
                "Padding": "Padding1",
                "ParentReportNormID": 4587,
                "ReportComponentName": "Kết quả kinh doanh",
                "ReportComponentNameEn": "Income Statement",
                "Unit": "",
                "UnitEn": "",
                "OrderType": 1,
                "OrderingComponent": 1,
                "RowNumber": 29,
                "ReportComponentTypeID": 12,
                "ChildTotal": 0,
                "Levels": 0,
                "Value1": 116372.0,
                "Value2": 216556.0,
                "Value3": 78302.0,
                "Value4": 53649.0,
                "Vl": null,
                "IsShowData": true
            },
            {
                "ID": 11,
                "ReportNormID": 4588,
                "Name": "Lãi cơ bản trên cổ phiếu (VNÐ)",
                "NameEn": "Earning per share (VND)",
                "NameMobile": "EPS",
                "NameMobileEn": "EPS",
                "CssStyle": "Normal",
                "Padding": "Padding1",
                "ParentReportNormID": 4588,
                "ReportComponentName": "Kết quả kinh doanh",
                "ReportComponentNameEn": "Income Statement",
                "Unit": "",
                "UnitEn": "",
                "OrderType": 1,
                "OrderingComponent": 1,
                "RowNumber": 30,
                "ReportComponentTypeID": 12,
                "ChildTotal": 0,
                "Levels": 0,
                "Value1": 1038.0,
                "Value2": 2675.0,
                "Value3": 1088.0,
                "Value4": 765.0,
                "Vl": null,
                "IsShowData": true
            }
        ],
        "Balance Sheet": [
            {
                "ID": 12,
                "ReportNormID": 4480,
                "Name": "Tài sản ngắn hạn",
                "NameEn": "Current assets",
                "NameMobile": "TSNH",
                "NameMobileEn": "Current assets",
                "CssStyle": "NormalB",
                "Padding": "Padding1",
                "ParentReportNormID": 4476,
                "ReportComponentName": "Cân đối kế toán",
                "ReportComponentNameEn": "Balance Sheet",
                "Unit": "",
                "UnitEn": "",
                "OrderType": 1,
                "OrderingComponent": 3,
                "RowNumber": 1,
                "ReportComponentTypeID": 14,
                "ChildTotal": 0,
                "Levels": 0,
                "Value1": 1728810.0,
                "Value2": 1492760.0,
                "Value3": 1282432.0,
                "Value4": 988147.0,
                "Vl": null,
                "IsShowData": true
            },
            {
                "ID": 13,
                "ReportNormID": 4774,
                "Name": "Tiền và các khoản tương đương tiền",
                "NameEn": "Cash and cash equivalents",
                "NameMobile": "Tiền & TĐ Tiền",
                "NameMobileEn": "CCE",
                "CssStyle": "Normal",
                "Padding": "Padding1",
                "ParentReportNormID": 5370,
                "ReportComponentName": "Cân đối kế toán",
                "ReportComponentNameEn": "Balance Sheet",
                "Unit": "",
                "UnitEn": "",
                "OrderType": 1,
                "OrderingComponent": 3,
                "RowNumber": 2,
                "ReportComponentTypeID": 14,
                "ChildTotal": 0,
                "Levels": 0,
                "Value1": 152041.0,
                "Value2": 3940.0,
                "Value3": 13927.0,
                "Value4": 5220.0,
                "Vl": null,
                "IsShowData": true
            },
            {
                "ID": 14,
                "ReportNormID": 4483,
                "Name": "Các khoản đầu tư tài chính ngắn hạn",
                "NameEn": "Short-term investments",
                "NameMobile": "ĐTTC ngắn hạn",
                "NameMobileEn": "Short-term inv.",
                "CssStyle": "Normal",
                "Padding": "Padding1",
                "ParentReportNormID": 5370,
                "ReportComponentName": "Cân đối kế toán",
                "ReportComponentNameEn": "Balance Sheet",
                "Unit": "",
                "UnitEn": "",
                "OrderType": 1,
                "OrderingComponent": 3,
                "RowNumber": 3,
                "ReportComponentTypeID": 14,
                "ChildTotal": 0,
                "Levels": 0,
                "Value1": null,
                "Value2": null,
                "Value3": null,
                "Value4": null,
                "Vl": null,
                "IsShowData": true
            },
            {
                "ID": 15,
                "ReportNormID": 4484,
                "Name": "Các khoản phải thu ngắn hạn",
                "NameEn": "Short-term receivables",
                "NameMobile": "Phải thu NH",
                "NameMobileEn": "Short-term rece.",
                "CssStyle": "Normal",
                "Padding": "Padding1",
                "ParentReportNormID": 5370,
                "ReportComponentName": "Cân đối kế toán",
                "ReportComponentNameEn": "Balance Sheet",
                "Unit": "",
                "UnitEn": "",
                "OrderType": 1,
                "OrderingComponent": 3,
                "RowNumber": 4,
                "ReportComponentTypeID": 14,
                "ChildTotal": 0,
                "Levels": 0,
                "Value1": 29144.0,
                "Value2": 32904.0,
                "Value3": 55797.0,
                "Value4": 162695.0,
                "Vl": null,
                "IsShowData": true
            },
            {
                "ID": 16,
                "ReportNormID": 4485,
                "Name": "Hàng tồn kho",
                "NameEn": "Inventories",
                "NameMobile": "HTK",
                "NameMobileEn": "Inventories",
                "CssStyle": "Normal",
                "Padding": "Padding1",
                "ParentReportNormID": 5370,
                "ReportComponentName": "Cân đối kế toán",
                "ReportComponentNameEn": "Balance Sheet",
                "Unit": "",
                "UnitEn": "",
                "OrderType": 1,
                "OrderingComponent": 3,
                "RowNumber": 5,
                "ReportComponentTypeID": 14,
                "ChildTotal": 0,
                "Levels": 0,
                "Value1": null,
                "Value2": null,
                "Value3": null,
                "Value4": null,
                "Vl": null,
                "IsShowData": true
            },
            {
                "ID": 17,
                "ReportNormID": 4481,
                "Name": "Tài sản dài hạn",
                "NameEn": "Non-current assets",
                "NameMobile": "TSDH",
                "NameMobileEn": "Non-CA",
                "CssStyle": "NormalB",
                "Padding": "Padding1",
                "ParentReportNormID": 4476,
                "ReportComponentName": "Cân đối kế toán",
                "ReportComponentNameEn": "Balance Sheet",
                "Unit": "",
                "UnitEn": "",
                "OrderType": 1,
                "OrderingComponent": 3,
                "RowNumber": 6,
                "ReportComponentTypeID": 14,
                "ChildTotal": 0,
                "Levels": 0,
                "Value1": 37431.0,
                "Value2": 37525.0,
                "Value3": 40982.0,
                "Value4": 104752.0,
                "Vl": null,
                "IsShowData": true
            },
            {
                "ID": 18,
                "ReportNormID": 4490,
                "Name": "Các khoản đầu tư tài chính dài hạn",
                "NameEn": "Long-term investments",
                "NameMobile": "ĐTTC dài hạn",
                "NameMobileEn": "Long-term inv.",
                "CssStyle": "Normal",
                "Padding": "Padding1",
                "ParentReportNormID": 5371,
                "ReportComponentName": "Cân đối kế toán",
                "ReportComponentNameEn": "Balance Sheet",
                "Unit": "",
                "UnitEn": "",
                "OrderType": 1,
                "OrderingComponent": 3,
                "RowNumber": 7,
                "ReportComponentTypeID": 14,
                "ChildTotal": 0,
                "Levels": 0,
                "Value1": 1500.0,
                "Value2": 1500.0,
                "Value3": 1500.0,
                "Value4": 53079.0,
                "Vl": null,
                "IsShowData": true
            },
            {
                "ID": 19,
                "ReportNormID": 4488,
                "Name": "Tài sản cố định",
                "NameEn": "Fixed assets",
                "NameMobile": "TSCĐ",
                "NameMobileEn": "Fixed assets",
                "CssStyle": "Normal",
                "Padding": "Padding1",
                "ParentReportNormID": 4481,
                "ReportComponentName": "Cân đối kế toán",
                "ReportComponentNameEn": "Balance Sheet",
                "Unit": "",
                "UnitEn": "",
                "OrderType": 1,
                "OrderingComponent": 3,
                "RowNumber": 8,
                "ReportComponentTypeID": 14,
                "ChildTotal": 0,
                "Levels": 0,
                "Value1": 2213.0,
                "Value2": 4665.0,
                "Value3": 9215.0,
                "Value4": 12607.0,
                "Vl": null,
                "IsShowData": true
            },
            {
                "ID": 20,
                "ReportNormID": 4489,
                "Name": "Bất động sản đầu tư",
                "NameEn": "Investment properties",
                "NameMobile": "BĐS ĐT",
                "NameMobileEn": "Inv. properties",
                "CssStyle": "Normal",
                "Padding": "Padding1",
                "ParentReportNormID": 4481,
                "ReportComponentName": "Cân đối kế toán",
                "ReportComponentNameEn": "Balance Sheet",
                "Unit": "",
                "UnitEn": "",
                "OrderType": 1,
                "OrderingComponent": 3,
                "RowNumber": 9,
                "ReportComponentTypeID": 14,
                "ChildTotal": 0,
                "Levels": 0,
                "Value1": null,
                "Value2": null,
                "Value3": null,
                "Value4": null,
                "Vl": null,
                "IsShowData": true
            },
            {
                "ID": 21,
                "ReportNormID": 4476,
                "Name": "Tổng cộng tài sản",
                "NameEn": "Total assets",
                "NameMobile": "Tổng TS",
                "NameMobileEn": "Total assets",
                "CssStyle": "NormalB",
                "Padding": "Padding1",
                "ParentReportNormID": 4476,
                "ReportComponentName": "Cân đối kế toán",
                "ReportComponentNameEn": "Balance Sheet",
                "Unit": "",
                "UnitEn": "",
                "OrderType": 1,
                "OrderingComponent": 3,
                "RowNumber": 10,
                "ReportComponentTypeID": 14,
                "ChildTotal": 0,
                "Levels": 0,
                "Value1": 1766241.0,
                "Value2": 1530285.0,
                "Value3": 1323415.0,
                "Value4": 1092898.0,
                "Vl": null,
                "IsShowData": true
            },
            {
                "ID": 22,
                "ReportNormID": 4477,
                "Name": "Nợ phải trả",
                "NameEn": "Liabilities",
                "NameMobile": "Nợ PT",
                "NameMobileEn": "Liabilities",
                "CssStyle": "NormalB",
                "Padding": "Padding1",
                "ParentReportNormID": 4479,
                "ReportComponentName": "Cân đối kế toán",
                "ReportComponentNameEn": "Balance Sheet",
                "Unit": "",
                "UnitEn": "",
                "OrderType": 1,
                "OrderingComponent": 3,
                "RowNumber": 11,
                "ReportComponentTypeID": 14,
                "ChildTotal": 0,
                "Levels": 0,
                "Value1": 345550.0,
                "Value2": 425966.0,
                "Value3": 398849.0,
                "Value4": 294833.0,
                "Vl": null,
                "IsShowData": true
            },
            {
                "ID": 23,
                "ReportNormID": 4493,
                "Name": "Nợ ngắn hạn",
                "NameEn": "Short-term liabilities",
                "NameMobile": "Nợ NH",
                "NameMobileEn": "Short-term liabi.",
                "CssStyle": "Normal",
                "Padding": "Padding1",
                "ParentReportNormID": 4477,
                "ReportComponentName": "Cân đối kế toán",
                "ReportComponentNameEn": "Balance Sheet",
                "Unit": "",
                "UnitEn": "",
                "OrderType": 1,
                "OrderingComponent": 3,
                "RowNumber": 12,
                "ReportComponentTypeID": 14,
                "ChildTotal": 0,
                "Levels": 0,
                "Value1": 212839.0,
                "Value2": 308568.0,
                "Value3": 66949.0,
                "Value4": 271185.0,
                "Vl": null,
                "IsShowData": true
            },
            {
                "ID": 24,
                "ReportNormID": 4496,
                "Name": "Nợ dài hạn",
                "NameEn": "Long-term liabilities",
                "NameMobile": "Nợ DH",
                "NameMobileEn": "Long-term liabi.",
                "CssStyle": "Normal",
                "Padding": "Padding1",
                "ParentReportNormID": 4477,
                "ReportComponentName": "Cân đối kế toán",
                "ReportComponentNameEn": "Balance Sheet",
                "Unit": "",
                "UnitEn": "",
                "OrderType": 1,
                "OrderingComponent": 3,
                "RowNumber": 13,
                "ReportComponentTypeID": 14,
                "ChildTotal": 0,
                "Levels": 0,
                "Value1": 132711.0,
                "Value2": 117398.0,
                "Value3": 331901.0,
                "Value4": 23648.0,
                "Vl": null,
                "IsShowData": true
            },
            {
                "ID": 25,
                "ReportNormID": 4478,
                "Name": "Vốn chủ sở hữu",
                "NameEn": "Owner's equity",
                "NameMobile": "VCSH",
                "NameMobileEn": "Owner's equity",
                "CssStyle": "NormalB",
                "Padding": "Padding1",
                "ParentReportNormID": 4479,
                "ReportComponentName": "Cân đối kế toán",
                "ReportComponentNameEn": "Balance Sheet",
                "Unit": "",
                "UnitEn": "",
                "OrderType": 1,
                "OrderingComponent": 3,
                "RowNumber": 14,
                "ReportComponentTypeID": 14,
                "ChildTotal": 0,
                "Levels": 0,
                "Value1": 1420691.0,
                "Value2": 1104319.0,
                "Value3": 924566.0,
                "Value4": 798066.0,
                "Vl": null,
                "IsShowData": true
            },
            {
                "ID": 26,
                "ReportNormID": 4542,
                "Name": "Vốn đầu tư của chủ sở hữu",
                "NameEn": "Charter capital",
                "NameMobile": "VĐL",
                "NameMobileEn": "Charter capital",
                "CssStyle": "Normal",
                "Padding": "Padding1",
                "ParentReportNormID": 5422,
                "ReportComponentName": "Cân đối kế toán",
                "ReportComponentNameEn": "Balance Sheet",
                "Unit": "",
                "UnitEn": "",
                "OrderType": 1,
                "OrderingComponent": 3,
                "RowNumber": 15,
                "ReportComponentTypeID": 14,
                "ChildTotal": 0,
                "Levels": 0,
                "Value1": 1161086.0,
                "Value2": 809646.0,
                "Value3": 736046.0,
                "Value4": 701002.0,
                "Vl": null,
                "IsShowData": true
            },
            {
                "ID": 27,
                "ReportNormID": 4543,
                "Name": "Thặng dư vốn cổ phần",
                "NameEn": "Share premium",
                "NameMobile": "Thặng dư VCP",
                "NameMobileEn": "Share premium",
                "CssStyle": "Normal",
                "Padding": "Padding1",
                "ParentReportNormID": 5422,
                "ReportComponentName": "Cân đối kế toán",
                "ReportComponentNameEn": "Balance Sheet",
                "Unit": "",
                "UnitEn": "",
                "OrderType": 1,
                "OrderingComponent": 3,
                "RowNumber": 16,
                "ReportComponentTypeID": 14,
                "ChildTotal": 0,
                "Levels": 0,
                "Value1": null,
                "Value2": null,
                "Value3": null,
                "Value4": null,
                "Vl": null,
                "IsShowData": true
            },
            {
                "ID": 28,
                "ReportNormID": 4551,
                "Name": "Lợi nhuận sau thuế chưa phân phối",
                "NameEn": "Retained earnings",
                "NameMobile": "LNST CPP",
                "NameMobileEn": "RE",
                "CssStyle": "Normal",
                "Padding": "Padding1",
                "ParentReportNormID": 4494,
                "ReportComponentName": "Cân đối kế toán",
                "ReportComponentNameEn": "Balance Sheet",
                "Unit": "",
                "UnitEn": "",
                "OrderType": 1,
                "OrderingComponent": 3,
                "RowNumber": 17,
                "ReportComponentTypeID": 14,
                "ChildTotal": 0,
                "Levels": 0,
                "Value1": 193060.0,
                "Value2": 239766.0,
                "Value3": 155268.0,
                "Value4": 62385.0,
                "Vl": null,
                "IsShowData": true
            },
            {
                "ID": 29,
                "ReportNormID": 4482,
                "Name": "Lợi ích của cổ đông thiểu số",
                "NameEn": "Minority interest",
                "NameMobile": "Lợi ích CĐTS",
                "NameMobileEn": "Mino. Interest",
                "CssStyle": "NormalB",
                "Padding": "Padding1",
                "ParentReportNormID": 4494,
                "ReportComponentName": "Cân đối kế toán",
                "ReportComponentNameEn": "Balance Sheet",
                "Unit": "",
                "UnitEn": "",
                "OrderType": 1,
                "OrderingComponent": 3,
                "RowNumber": 18,
                "ReportComponentTypeID": 14,
                "ChildTotal": 0,
                "Levels": 0,
                "Value1": null,
                "Value2": null,
                "Value3": null,
                "Value4": 9930.0,
                "Vl": null,
                "IsShowData": true
            },
            {
                "ID": 30,
                "ReportNormID": 4479,
                "Name": "Tổng cộng nguồn vốn",
                "NameEn": "Total owner's equity and liabilities",
                "NameMobile": "Tổng NV",
                "NameMobileEn": "E&L",
                "CssStyle": "NormalB",
                "Padding": "Padding1",
                "ParentReportNormID": 4479,
                "ReportComponentName": "Cân đối kế toán",
                "ReportComponentNameEn": "Balance Sheet",
                "Unit": "",
                "UnitEn": "",
                "OrderType": 1,
                "OrderingComponent": 3,
                "RowNumber": 19,
                "ReportComponentTypeID": 14,
                "ChildTotal": 0,
                "Levels": 0,
                "Value1": 1766241.0,
                "Value2": 1530285.0,
                "Value3": 1323415.0,
                "Value4": 1092898.0,
                "Vl": null,
                "IsShowData": true
            }
        ],
        "RATIOS": [
            {
                "ID": 31,
                "ReportNormID": 53,
                "Name": "Thu nhập trên mỗi cổ phần của 4 quý gần nhất (EPS)",
                "NameEn": "Trailing EPS",
                "NameMobile": "Thu nhập trên mỗi cổ phần của 4 quý gần nhất (EPS)",
                "NameMobileEn": "Trailing EPS",
                "CssStyle": "",
                "Padding": "Padding1",
                "ParentReportNormID": 0,
                "ReportComponentName": "Chỉ số tài chính",
                "ReportComponentNameEn": "RATIOS",
                "Unit": "VNĐ",
                "UnitEn": "VND",
                "OrderType": 2,
                "OrderingComponent": 1,
                "RowNumber": 1,
                "ReportComponentTypeID": -1,
                "ChildTotal": 0,
                "Levels": 0,
                "Value1": 1099.0,
                "Value2": 2775.0,
                "Value3": 1090.0,
                "Value4": 786.0,
                "Vl": null,
                "IsShowData": true
            },
            {
                "ID": 32,
                "ReportNormID": 54,
                "Name": "Giá trị sổ sách của cổ phiếu (BVPS)",
                "NameEn": "Book value per share (BVPS)",
                "NameMobile": "Giá trị sổ sách của cổ phiếu (BVPS)",
                "NameMobileEn": "Book value per share (BVPS)",
                "CssStyle": "",
                "Padding": "Padding1",
                "ParentReportNormID": 0,
                "ReportComponentName": "Chỉ số tài chính",
                "ReportComponentNameEn": "RATIOS",
                "Unit": "VNĐ",
                "UnitEn": "VND",
                "OrderType": 2,
                "OrderingComponent": 1,
                "RowNumber": 2,
                "ReportComponentTypeID": -1,
                "ChildTotal": 0,
                "Levels": 0,
                "Value1": 12236.0,
                "Value2": 13640.0,
                "Value3": 12561.0,
                "Value4": 11385.0,
                "Vl": null,
                "IsShowData": true
            },
            {
                "ID": 33,
                "ReportNormID": 55,
                "Name": "Chỉ số giá thị trường trên thu nhập (P/E)",
                "NameEn": "P/E",
                "NameMobile": "Chỉ số giá thị trường trên thu nhập (P/E)",
                "NameMobileEn": "P/E",
                "CssStyle": "",
                "Padding": "Padding1",
                "ParentReportNormID": 0,
                "ReportComponentName": "Chỉ số tài chính",
                "ReportComponentNameEn": "RATIOS",
                "Unit": "Lần",
                "UnitEn": "Times",
                "OrderType": 2,
                "OrderingComponent": 1,
                "RowNumber": 3,
                "ReportComponentTypeID": -1,
                "ChildTotal": 0,
                "Levels": 0,
                "Value1": 5.1,
                "Value2": 3.35,
                "Value3": 9.72,
                "Value4": 7.0,
                "Vl": null,
                "IsShowData": true
            },
            {
                "ID": 34,
                "ReportNormID": 57,
                "Name": "Chỉ số giá thị trường trên giá trị sổ sách (P/B)",
                "NameEn": "P/B",
                "NameMobile": "Chỉ số giá thị trường trên giá trị sổ sách (P/B)",
                "NameMobileEn": "P/B",
                "CssStyle": "",
                "Padding": "Padding1",
                "ParentReportNormID": 0,
                "ReportComponentName": "Chỉ số tài chính",
                "ReportComponentNameEn": "RATIOS",
                "Unit": "Lần",
                "UnitEn": "Times",
                "OrderType": 2,
                "OrderingComponent": 1,
                "RowNumber": 4,
                "ReportComponentTypeID": -1,
                "ChildTotal": 0,
                "Levels": 0,
                "Value1": 0.46,
                "Value2": 0.68,
                "Value3": 0.84,
                "Value4": 0.48,
                "Vl": null,
                "IsShowData": true
            },
            {
                "ID": 35,
                "ReportNormID": 41,
                "Name": "Tỷ suất lợi nhuận gộp biên",
                "NameEn": "Gross profit margin",
                "NameMobile": "Tỷ suất lợi nhuận gộp biên",
                "NameMobileEn": "Gross profit margin",
                "CssStyle": "",
                "Padding": "Padding1",
                "ParentReportNormID": 0,
                "ReportComponentName": "Chỉ số tài chính",
                "ReportComponentNameEn": "RATIOS",
                "Unit": "%",
                "UnitEn": "%",
                "OrderType": 2,
                "OrderingComponent": 1,
                "RowNumber": 5,
                "ReportComponentTypeID": -1,
                "ChildTotal": 0,
                "Levels": 0,
                "Value1": 45.79,
                "Value2": 67.0,
                "Value3": 44.57,
                "Value4": 55.61,
                "Vl": null,
                "IsShowData": true
            },
            {
                "ID": 36,
                "ReportNormID": 44,
                "Name": "Tỷ suất sinh lợi trên doanh thu thuần",
                "NameEn": "Net profit margin",
                "NameMobile": "Tỷ suất sinh lợi trên doanh thu thuần",
                "NameMobileEn": "Net profit margin",
                "CssStyle": "",
                "Padding": "Padding1",
                "ParentReportNormID": 0,
                "ReportComponentName": "Chỉ số tài chính",
                "ReportComponentNameEn": "RATIOS",
                "Unit": "%",
                "UnitEn": "%",
                "OrderType": 2,
                "OrderingComponent": 1,
                "RowNumber": 6,
                "ReportComponentTypeID": -1,
                "ChildTotal": 0,
                "Levels": 0,
                "Value1": 26.63,
                "Value2": 47.87,
                "Value3": 20.2,
                "Value4": 28.67,
                "Vl": null,
                "IsShowData": true
            },
            {
                "ID": 37,
                "ReportNormID": 45,
                "Name": "Tỷ suất lợi nhuận trên vốn chủ sở hữu bình quân (ROEA)",
                "NameEn": "ROE",
                "NameMobile": "Tỷ suất lợi nhuận trên vốn chủ sở hữu bình quân (ROEA)",
                "NameMobileEn": "ROE",
                "CssStyle": "",
                "Padding": "Padding1",
                "ParentReportNormID": 0,
                "ReportComponentName": "Chỉ số tài chính",
                "ReportComponentNameEn": "RATIOS",
                "Unit": "%",
                "UnitEn": "%",
                "OrderType": 2,
                "OrderingComponent": 1,
                "RowNumber": 7,
                "ReportComponentTypeID": -1,
                "ChildTotal": 0,
                "Levels": 0,
                "Value1": 9.22,
                "Value2": 21.35,
                "Value3": 9.09,
                "Value4": 6.86,
                "Vl": null,
                "IsShowData": true
            },
            {
                "ID": 38,
                "ReportNormID": 47,
                "Name": "Tỷ suất sinh lợi trên tổng tài sản bình quân (ROAA)",
                "NameEn": "ROA",
                "NameMobile": "Tỷ suất sinh lợi trên tổng tài sản bình quân (ROAA)",
                "NameMobileEn": "ROA",
                "CssStyle": "",
                "Padding": "Padding1",
                "ParentReportNormID": 0,
                "ReportComponentName": "Chỉ số tài chính",
                "ReportComponentNameEn": "RATIOS",
                "Unit": "%",
                "UnitEn": "%",
                "OrderType": 2,
                "OrderingComponent": 1,
                "RowNumber": 8,
                "ReportComponentTypeID": -1,
                "ChildTotal": 0,
                "Levels": 0,
                "Value1": 7.06,
                "Value2": 15.18,
                "Value3": 6.48,
                "Value4": 5.28,
                "Vl": null,
                "IsShowData": true
            },
            {
                "ID": 39,
                "ReportNormID": 1,
                "Name": "Tỷ số thanh toán bằng tiền mặt",
                "NameEn": "Cash ratio",
                "NameMobile": "Tỷ số thanh toán bằng tiền mặt",
                "NameMobileEn": "Cash ratio",
                "CssStyle": "",
                "Padding": "Padding1",
                "ParentReportNormID": 0,
                "ReportComponentName": "Chỉ số tài chính",
                "ReportComponentNameEn": "RATIOS",
                "Unit": "Lần",
                "UnitEn": "Times",
                "OrderType": 2,
                "OrderingComponent": 1,
                "RowNumber": 9,
                "ReportComponentTypeID": -1,
                "ChildTotal": 0,
                "Levels": 0,
                "Value1": 0.71,
                "Value2": 0.01,
                "Value3": 0.21,
                "Value4": 0.02,
                "Vl": null,
                "IsShowData": true
            },
            {
                "ID": 40,
                "ReportNormID": 4,
                "Name": "Tỷ số thanh toán hiện hành (ngắn hạn)",
                "NameEn": "Short-term ratio",
                "NameMobile": "Tỷ số thanh toán hiện hành (ngắn hạn)",
                "NameMobileEn": "Short-term ratio",
                "CssStyle": "",
                "Padding": "Padding1",
                "ParentReportNormID": 0,
                "ReportComponentName": "Chỉ số tài chính",
                "ReportComponentNameEn": "RATIOS",
                "Unit": "Lần",
                "UnitEn": "Times",
                "OrderType": 2,
                "OrderingComponent": 1,
                "RowNumber": 10,
                "ReportComponentTypeID": -1,
                "ChildTotal": 0,
                "Levels": 0,
                "Value1": 8.12,
                "Value2": 4.84,
                "Value3": 19.16,
                "Value4": 3.64,
                "Vl": null,
                "IsShowData": true
            },
            {
                "ID": 41,
                "ReportNormID": 8,
                "Name": "Tỷ số Nợ trên Tổng tài sản",
                "NameEn": "Liabilities to assets",
                "NameMobile": "Tỷ số Nợ trên Tổng tài sản",
                "NameMobileEn": "Liabilities to assets",
                "CssStyle": "",
                "Padding": "Padding1",
                "ParentReportNormID": 0,
                "ReportComponentName": "Chỉ số tài chính",
                "ReportComponentNameEn": "RATIOS",
                "Unit": "%",
                "UnitEn": "%",
                "OrderType": 2,
                "OrderingComponent": 1,
                "RowNumber": 11,
                "ReportComponentTypeID": -1,
                "ChildTotal": 0,
                "Levels": 0,
                "Value1": 19.56,
                "Value2": 27.84,
                "Value3": 30.14,
                "Value4": 26.98,
                "Vl": null,
                "IsShowData": true
            },
            {
                "ID": 42,
                "ReportNormID": 12,
                "Name": "Tỷ số Nợ trên Vốn chủ sở hữu",
                "NameEn": "Liabilities to equity",
                "NameMobile": "Tỷ số Nợ trên Vốn chủ sở hữu",
                "NameMobileEn": "Liabilities to equity",
                "CssStyle": "",
                "Padding": "Padding1",
                "ParentReportNormID": 0,
                "ReportComponentName": "Chỉ số tài chính",
                "ReportComponentNameEn": "RATIOS",
                "Unit": "%",
                "UnitEn": "%",
                "OrderType": 2,
                "OrderingComponent": 1,
                "RowNumber": 12,
                "ReportComponentTypeID": -1,
                "ChildTotal": 0,
                "Levels": 0,
                "Value1": 24.32,
                "Value2": 38.57,
                "Value3": 43.14,
                "Value4": 36.94,
                "Vl": null,
                "IsShowData": true
            }
        ]
    },
    [
        {
            "AuditedStatusCode": "SX",
            "Description": "Soát xét",
            "DescriptionEn": "Reviewed"
        },
        {
            "AuditedStatusCode": "CKT",
            "Description": "Chưa kiểm toán",
            "DescriptionEn": "Unaudited"
        },
        {
            "AuditedStatusCode": "KT",
            "Description": "Kiểm toán",
            "DescriptionEn": "Audited"
        }
    ],
    [
        {
            "UnitedCode": "HN",
            "UnitedName": "Hợp nhất",
            "UnitedNameEN": "Consolidated"
        },
        {
            "UnitedCode": "ĐL",
            "UnitedName": "Đơn lẻ",
            "UnitedNameEN": "Stand-alone"
        },
        {
            "UnitedCode": "CTM",
            "UnitedName": "Công ty mẹ",
            "UnitedNameEN": "Parent Company"
        }
    ]
]